printhelloworld/__init__.py
printhelloworld/printhelloworld.py
printhelloworld-0.0.4.dist-info/License.txt
printhelloworld-0.0.4.dist-info/METADATA
printhelloworld-0.0.4.dist-info/WHEEL
printhelloworld-0.0.4.dist-info/top_level.txt
printhelloworld-0.0.4.dist-info/RECORD
