Metadata-Version: 2.1
Name: printhelloworld
Version: 0.0.4
Summary: Minore bug fix
Home-page: UNKNOWN
Author: Advait Shiralkar
Author-email: advaitshiralkar2@gmail.com
License: UNKNOWN
Platform: UNKNOWN
Classifier: Development Status :: 1 - Planning
Classifier: Intended Audience :: Developers
Classifier: Programming Language :: Python :: 3
Classifier: Operating System :: Unix
Classifier: Operating System :: MacOS :: MacOS X
Classifier: Operating System :: Microsoft :: Windows
License-File: License.txt
